skillet/__init__.py
skillet/config.py
skillet/errors.py
skillet/errors_test.py
skillet/py.typed
skillet/_internal/__init__.py
skillet/_internal/async_utils.py
skillet/_internal/async_utils_test.py
skillet/_internal/cache.py
skillet/_internal/cache_test.py
skillet/_internal/lock.py
skillet/_internal/lock_test.py
skillet/_internal/sdk.py
skillet/_internal/sdk_test.py
skillet/_internal/text.py
skillet/_internal/text_test.py
skillet/_internal/types.py
skillet/_internal/types_test.py
skillet/cli/__init__.py
skillet/cli/cli_test.py
skillet/cli/main.py
skillet/cli/main_test.py
skillet/cli/commands/__init__.py
skillet/cli/commands/compare/__init__.py
skillet/cli/commands/compare/compare.py
skillet/cli/commands/compare/compare_test.py
skillet/cli/commands/compare/format_delta.py
skillet/cli/commands/create/__init__.py
skillet/cli/commands/create/create.py
skillet/cli/commands/create/create_test.py
skillet/cli/commands/eval/__init__.py
skillet/cli/commands/eval/eval.py
skillet/cli/commands/eval/eval_test.py
skillet/cli/commands/eval/get_scripts_from_evals.py
skillet/cli/commands/eval/get_scripts_from_evals_test.py
skillet/cli/commands/eval/models.py
skillet/cli/commands/eval/prompt_for_script_confirmation.py
skillet/cli/commands/eval/prompt_for_script_confirmation_test.py
skillet/cli/commands/eval/summarize.py
skillet/cli/commands/eval/summarize.txt
skillet/cli/commands/eval/summarize_test.py
skillet/cli/commands/generate_evals/__init__.py
skillet/cli/commands/generate_evals/generate_evals.py
skillet/cli/commands/generate_evals/generate_evals_test.py
skillet/cli/commands/lint/__init__.py
skillet/cli/commands/lint/lint.py
skillet/cli/commands/lint/lint_test.py
skillet/cli/commands/lint/print_rules.py
skillet/cli/commands/lint/print_rules_test.py
skillet/cli/commands/tune/__init__.py
skillet/cli/commands/tune/output_path.py
skillet/cli/commands/tune/print_result.py
skillet/cli/commands/tune/print_result_test.py
skillet/cli/commands/tune/tune.py
pyskillet-0.2.13.dist-info/METADATA
pyskillet-0.2.13.dist-info/WHEEL
pyskillet-0.2.13.dist-info/entry_points.txt
pyskillet-0.2.13.dist-info/licenses/LICENSE
pyskillet-0.2.13.dist-info/RECORD
