Metadata-Version: 2.4
Name: pyskillet
Version: 0.2.13
Summary: Evaluation-driven Claude Code skill development
License-File: LICENSE
Requires-Python: >=3.12
Requires-Dist: claude-agent-sdk
Requires-Dist: cyclopts>=3.0
Requires-Dist: dspy>=2.6
Requires-Dist: pyyaml>=6.0
Requires-Dist: rich>=13.0
Provides-Extra: dev
Requires-Dist: bandit>=1.7; extra == 'dev'
Requires-Dist: pre-commit>=4.0; extra == 'dev'
Requires-Dist: pytest-asyncio>=0.24; extra == 'dev'
Requires-Dist: pytest-cov>=4.0; extra == 'dev'
Requires-Dist: pytest-describe>=2.0; extra == 'dev'
Requires-Dist: pytest-watcher>=0.4; extra == 'dev'
Requires-Dist: pytest>=8.0; extra == 'dev'
Requires-Dist: ruff>=0.8; extra == 'dev'
Requires-Dist: rust-just>=1.0; extra == 'dev'
Requires-Dist: ty>=0.0.1a7; extra == 'dev'
